antivirals/__init__.py
antivirals/__main__.py
antivirals/chem.py
antivirals/data.py
antivirals/parser.cpython-37m-darwin.so
antivirals/parser.py
antivirals/schema.py
antivirals/extras/__init__.py
antivirals/extras/optim.py
antivirals-0.0.3.dist-info/LICENSE
antivirals-0.0.3.dist-info/METADATA
antivirals-0.0.3.dist-info/WHEEL
antivirals-0.0.3.dist-info/entry_points.txt
antivirals-0.0.3.dist-info/top_level.txt
antivirals-0.0.3.dist-info/RECORD
