Metadata-Version: 2.1
Name: antivirals
Version: 0.0.3
Summary: Finding antivirals for the novel coronavirus.
Home-page: https://www.github.com/bnext-iqt/antivirals
Author: JJ Ben-Joseph
Author-email: jbenjoseph@iqt.org
License: Apache
Keywords: machine_learning artificial_intelligence medicine devops
Platform: UNKNOWN
Classifier: Topic :: Scientific/Engineering :: Artificial Intelligence
Classifier: Topic :: Scientific/Engineering :: Chemistry
Classifier: Topic :: Scientific/Engineering :: Medical Science Apps.
Classifier: Development Status :: 2 - Pre-Alpha
Classifier: Intended Audience :: Developers
Classifier: Intended Audience :: Science/Research
Classifier: License :: OSI Approved :: Apache Software License
Classifier: Programming Language :: Python :: 3 :: Only
Classifier: Programming Language :: Python :: 3.8
Classifier: Operating System :: OS Independent
Requires-Python: >=3.6
Requires-Dist: tqdm
Requires-Dist: sqlalchemy
Requires-Dist: numpy
Requires-Dist: scikit-learn
Requires-Dist: pandas
Requires-Dist: fire
Requires-Dist: gensim
Provides-Extra: optim
Requires-Dist: sigopt ; extra == 'optim'
